dmq/__init__.py
dmq/abc/__init__.py
dmq/abc/backend.py
dmq/abc/broker.py
dmq/abc/serializer.py
dmq/backends/__init__.py
dmq/backends/memory.py
dmq/backends/postgres_backend.py
dmq/backends/redis_backend.py
dmq/brokers/__init__.py
dmq/brokers/memory.py
dmq/brokers/redis.py
dmq/brokers/redis_pubsub.py
dmq/callback.py
dmq/cli/__init__.py
dmq/cli/cli.py
dmq/cli/utils.py
dmq/event_router.py
dmq/events/__init__.py
dmq/events/core.py
dmq/events/shortcuts.py
dmq/execution_mode.py
dmq/guarantees.py
dmq/manager.py
dmq/partitioning.py
dmq/retry.py
dmq/runtime.py
dmq/scheduler.py
dmq/serializers/__init__.py
dmq/serializers/json.py
dmq/serializers/msgpack.py
dmq/serializers/pickle.py
dmq/task.py
dmq/threaded_worker.py
dmq/topic.py
dmq/types.py
dmq/user_event.py
dmq/util/__init__.py
dmq/util/misc.py
dmq/worker.py
dmq/worker_pool.py
dmq-0.0.3.dist-info/WHEEL
dmq-0.0.3.dist-info/entry_points.txt
dmq-0.0.3.dist-info/METADATA
dmq-0.0.3.dist-info/RECORD
